oraculo/__init__.py
oraculo_gpc-0.0.1.dist-info/AUTHORS.rst
oraculo_gpc-0.0.1.dist-info/LICENSE
oraculo_gpc-0.0.1.dist-info/METADATA
oraculo_gpc-0.0.1.dist-info/WHEEL
oraculo_gpc-0.0.1.dist-info/top_level.txt
oraculo_gpc-0.0.1.dist-info/RECORD
