Metadata-Version: 2.1
Name: oraculo-gpc
Version: 0.0.1
Summary: Python Boilerplate contains all the boilerplate you need to create a Python package.
Home-page: https://github.com/erasmo07/oraculo
Author: Erasmo Montes
Author-email: emontes@puntacana.com
License: MIT license
Keywords: oraculo
Platform: UNKNOWN
Classifier: Development Status :: 2 - Pre-Alpha
Classifier: Intended Audience :: Developers
Classifier: License :: OSI Approved :: MIT License
Classifier: Natural Language :: English
Classifier: Programming Language :: Python :: 2
Classifier: Programming Language :: Python :: 2.7
Classifier: Programming Language :: Python :: 3
Classifier: Programming Language :: Python :: 3.4
Classifier: Programming Language :: Python :: 3.5
Classifier: Programming Language :: Python :: 3.6
Classifier: Programming Language :: Python :: 3.7
Requires-Dist: requests
Requires-Dist: pytest-runner
